odoo/addons/base_external_dbsource_mysql/README.rst
odoo/addons/base_external_dbsource_mysql/__init__.py
odoo/addons/base_external_dbsource_mysql/__manifest__.py
odoo/addons/base_external_dbsource_mysql/demo/base_external_dbsource.xml
odoo/addons/base_external_dbsource_mysql/i18n/base_external_dbsource_mysql.pot
odoo/addons/base_external_dbsource_mysql/i18n/de.po
odoo/addons/base_external_dbsource_mysql/i18n/es.po
odoo/addons/base_external_dbsource_mysql/i18n/hr.po
odoo/addons/base_external_dbsource_mysql/i18n/nl_NL.po
odoo/addons/base_external_dbsource_mysql/i18n/pt_BR.po
odoo/addons/base_external_dbsource_mysql/i18n/sl.po
odoo/addons/base_external_dbsource_mysql/i18n/tr.po
odoo/addons/base_external_dbsource_mysql/models/__init__.py
odoo/addons/base_external_dbsource_mysql/models/base_external_dbsource.py
odoo/addons/base_external_dbsource_mysql/readme/CONFIGURE.rst
odoo/addons/base_external_dbsource_mysql/readme/CONTRIBUTORS.rst
odoo/addons/base_external_dbsource_mysql/readme/DESCRIPTION.rst
odoo/addons/base_external_dbsource_mysql/readme/INSTALL.rst
odoo/addons/base_external_dbsource_mysql/readme/ROADMAP.rst
odoo/addons/base_external_dbsource_mysql/readme/USAGE.rst
odoo/addons/base_external_dbsource_mysql/static/description/icon.png
odoo/addons/base_external_dbsource_mysql/static/description/index.html
odoo/addons/base_external_dbsource_mysql/tests/__init__.py
odoo/addons/base_external_dbsource_mysql/tests/test_base_external_dbsource.py
odoo11_addon_base_external_dbsource_mysql-11.0.1.0.0.99.dev6.dist-info/METADATA
odoo11_addon_base_external_dbsource_mysql-11.0.1.0.0.99.dev6.dist-info/WHEEL
odoo11_addon_base_external_dbsource_mysql-11.0.1.0.0.99.dev6.dist-info/top_level.txt
odoo11_addon_base_external_dbsource_mysql-11.0.1.0.0.99.dev6.dist-info/RECORD
